{
  "version": 2,
  "extractor": "papercropper",
  "figures": [
    {
      "url": "assets/figures/arxiv/2606.12217v1/fig-001.webp",
      "caption": "",
      "page": 0,
      "index": 1,
      "width": 1443,
      "height": 583,
      "label": "Figure"
    },
    {
      "url": "assets/figures/arxiv/2606.12217v1/fig-002.webp",
      "caption": "",
      "page": 0,
      "index": 2,
      "width": 1346,
      "height": 378,
      "label": "Figure"
    },
    {
      "url": "assets/figures/arxiv/2606.12217v1/fig-003.webp",
      "caption": "",
      "page": 0,
      "index": 3,
      "width": 1344,
      "height": 490,
      "label": "Figure"
    },
    {
      "url": "assets/figures/arxiv/2606.12217v1/fig-004.webp",
      "caption": "",
      "page": 0,
      "index": 4,
      "width": 1379,
      "height": 594,
      "label": "Figure"
    },
    {
      "url": "assets/figures/arxiv/2606.12217v1/fig-005.webp",
      "caption": "",
      "page": 0,
      "index": 5,
      "width": 1336,
      "height": 380,
      "label": "Figure"
    },
    {
      "url": "assets/figures/arxiv/2606.12217v1/fig-006.webp",
      "caption": "",
      "page": 0,
      "index": 6,
      "width": 635,
      "height": 322,
      "label": "Figure"
    },
    {
      "url": "assets/figures/arxiv/2606.12217v1/fig-007.webp",
      "caption": "",
      "page": 0,
      "index": 7,
      "width": 1345,
      "height": 815,
      "label": "Figure"
    },
    {
      "url": "assets/figures/arxiv/2606.12217v1/fig-008.webp",
      "caption": "",
      "page": 0,
      "index": 8,
      "width": 1427,
      "height": 641,
      "label": "Figure"
    },
    {
      "url": "assets/figures/arxiv/2606.12217v1/fig-009.webp",
      "caption": "",
      "page": 0,
      "index": 9,
      "width": 1433,
      "height": 543,
      "label": "Figure"
    },
    {
      "url": "assets/figures/arxiv/2606.12217v1/fig-010.webp",
      "caption": "",
      "page": 0,
      "index": 10,
      "width": 687,
      "height": 425,
      "label": "Figure"
    },
    {
      "url": "assets/figures/arxiv/2606.12217v1/fig-011.webp",
      "caption": "",
      "page": 0,
      "index": 11,
      "width": 694,
      "height": 422,
      "label": "Figure"
    },
    {
      "url": "assets/figures/arxiv/2606.12217v1/fig-012.webp",
      "caption": "",
      "page": 0,
      "index": 12,
      "width": 1441,
      "height": 2151,
      "label": "Figure"
    },
    {
      "url": "assets/figures/arxiv/2606.12217v1/fig-013.webp",
      "caption": "",
      "page": 0,
      "index": 13,
      "width": 1423,
      "height": 535,
      "label": "Figure"
    },
    {
      "url": "assets/figures/arxiv/2606.12217v1/fig-014.webp",
      "caption": "",
      "page": 0,
      "index": 14,
      "width": 1358,
      "height": 1072,
      "label": "Figure"
    },
    {
      "url": "assets/figures/arxiv/2606.12217v1/fig-015.webp",
      "caption": "",
      "page": 0,
      "index": 15,
      "width": 1361,
      "height": 1275,
      "label": "Figure"
    },
    {
      "url": "assets/figures/arxiv/2606.12217v1/fig-016.webp",
      "caption": "",
      "page": 0,
      "index": 16,
      "width": 1400,
      "height": 404,
      "label": "Figure"
    }
  ]
}