{
  "version": 2,
  "extractor": "papercropper",
  "tables": [
    {
      "url": "assets/tables/arxiv/2605.12369v1/table-001.webp",
      "caption": "",
      "page": 0,
      "index": 1,
      "width": 921,
      "height": 705,
      "label": "Table"
    },
    {
      "url": "assets/tables/arxiv/2605.12369v1/table-002.webp",
      "caption": "",
      "page": 0,
      "index": 2,
      "width": 1799,
      "height": 780,
      "label": "Table"
    },
    {
      "url": "assets/tables/arxiv/2605.12369v1/table-003.webp",
      "caption": "",
      "page": 0,
      "index": 3,
      "width": 1189,
      "height": 427,
      "label": "Table"
    },
    {
      "url": "assets/tables/arxiv/2605.12369v1/table-004.webp",
      "caption": "",
      "page": 0,
      "index": 4,
      "width": 1635,
      "height": 747,
      "label": "Table"
    },
    {
      "url": "assets/tables/arxiv/2605.12369v1/table-005.webp",
      "caption": "",
      "page": 0,
      "index": 5,
      "width": 1274,
      "height": 2028,
      "label": "Table"
    },
    {
      "url": "assets/tables/arxiv/2605.12369v1/table-006.webp",
      "caption": "",
      "page": 0,
      "index": 6,
      "width": 1780,
      "height": 637,
      "label": "Table"
    },
    {
      "url": "assets/tables/arxiv/2605.12369v1/table-007.webp",
      "caption": "",
      "page": 0,
      "index": 7,
      "width": 1457,
      "height": 213,
      "label": "Table"
    },
    {
      "url": "assets/tables/arxiv/2605.12369v1/table-008.webp",
      "caption": "",
      "page": 0,
      "index": 8,
      "width": 1615,
      "height": 350,
      "label": "Table"
    },
    {
      "url": "assets/tables/arxiv/2605.12369v1/table-009.webp",
      "caption": "",
      "page": 0,
      "index": 9,
      "width": 1416,
      "height": 215,
      "label": "Table"
    },
    {
      "url": "assets/tables/arxiv/2605.12369v1/table-010.webp",
      "caption": "",
      "page": 0,
      "index": 10,
      "width": 1406,
      "height": 261,
      "label": "Table"
    },
    {
      "url": "assets/tables/arxiv/2605.12369v1/table-011.webp",
      "caption": "",
      "page": 0,
      "index": 11,
      "width": 1367,
      "height": 1786,
      "label": "Table"
    },
    {
      "url": "assets/tables/arxiv/2605.12369v1/table-012.webp",
      "caption": "",
      "page": 0,
      "index": 12,
      "width": 1687,
      "height": 1294,
      "label": "Table"
    },
    {
      "url": "assets/tables/arxiv/2605.12369v1/table-013.webp",
      "caption": "",
      "page": 0,
      "index": 13,
      "width": 1778,
      "height": 347,
      "label": "Table"
    },
    {
      "url": "assets/tables/arxiv/2605.12369v1/table-014.webp",
      "caption": "",
      "page": 0,
      "index": 14,
      "width": 1128,
      "height": 310,
      "label": "Table"
    }
  ]
}